{
    "users": [{
        "username": "user",
        "password": "password"
      }],
      

    "teams": [{
        "teamId": "string",
        "name": "string",
        "members": [
            "string"
        ],
        "projects": [
            "string"
        ]
    }],


    "projects": [{
        "id": "string",
        "title": "string",
        "description": "string",
        "task": [
            "string"
        ]
    }],


    "tasks": [{
        "id": "string",
        "title": "string",
        "description": "string",
        "dueDate": "dateTime",
        "completed": "boolean"
    }]

}